{
  "username": "yabbieo",
  "album": ["Cute cat"],
  "init_jumlah_photo": 50,
  "admob_banner_id": "ca-app-pub-9160001534541342/4653119701",
  "admob_interstitial_id": "ca-app-pub-9160001534541342/9330731319",
  "admob_native_id": "ca-app-pub-9160001534541342/2382179587",
  "admob_rewarded_id": "ca-app-pub-9160001534541342/4341294361",
  "admob_rewarded_interstitial_id": "ca-app-pub-9160001534541342/7983643010",
  "admob_open_app_id": "ca-app-pub-9160001534541342/3689174784",
  "admob_hpk_1": "kpop",
  "admob_hpk_2": "fashion",
  "admob_hpk_3": "plastic surgery",
  "admob_hpk_4": "bts",
  "admob_hpk_5": "insurance",
  "startapp_app_id": "",
  "unity_id": "4828560",
  "unity_banner": "Banner_Android",
  "unity_interstitial": "Interstitial_Android",
  "interstitial_inverval": 10,
  "list_ads": ["ADMOB", "UNITY", "STARTAPP"]
}
